{
  "kind": "collectionType",
  "collectionName": "leads",
  "info": {
    "singularName": "lead",
    "pluralName": "leads",
    "displayName": "Lead",
    "description": ""
  },
  "options": {
    "draftAndPublish": true
  },
  "pluginOptions": {},
  "attributes": {
    "name": {
      "type": "string",
      "required": true
    },
    "service": {
      "type": "string"
    },
    "description": {
      "type": "text"
    },
    "phone_num": {
      "type": "string"
    },
    "email": {
      "type": "email",
      "required": true,
      "unique": true
    },
    "active": {
      "type": "boolean",
      "required": true,
      "default": false
    },
    "supabase_user_id": {
      "type": "string",
      "required": false
    },
    "lead_uuid": {
      "type": "string",
      "required": true,
      "unique": true
    },
    "company_name": {
      "type": "string"
    },
    "website_url": {
      "type": "string"
    },
    "monthly_marketing_investment": {
      "type": "string"
    },
    "project_timeline": {
      "type": "string"
    },
    "business_description": {
      "type": "string"
    },
    "action_prompt": {
      "type": "string"
    },
    "growth_investment_acknowledgement": {
      "type": "boolean"
    }
  }
}
